main.py
utils.py
tools/__init__.py
tools/chart_tools.py
tools/dashboard_tools.py
tools/database_tools.py
tools/dataset_tools.py
tools/sqllab_tools.py
superset_mcp-0.6.0.dist-info/METADATA
superset_mcp-0.6.0.dist-info/WHEEL
superset_mcp-0.6.0.dist-info/entry_points.txt
superset_mcp-0.6.0.dist-info/top_level.txt
superset_mcp-0.6.0.dist-info/RECORD
