Metadata-Version: 2.4
Name: superset-mcp
Version: 0.6.0
Summary: Model Control Protocol (MCP) server for Apache Superset integration with AI assistants
Author: 
License: MIT
Classifier: Development Status :: 4 - Beta
Classifier: Intended Audience :: Developers
Classifier: Programming Language :: Python :: 3
Classifier: License :: OSI Approved :: MIT License
Requires-Python: >=3.10
Requires-Dist: httpx>=0.28.0
Requires-Dist: mcp[cli]>=1.4.0
Requires-Dist: uvicorn>=0.34.0
Requires-Dist: python-dotenv>=1.0.0
Requires-Dist: pydantic>=2.11.7
Requires-Dist: prison>=0.2.1
Requires-Dist: jsonpatch>=1.33
